README.md
setup.py
kmux_redis/__init__.py
kmux_redis/kmux_redis.py
kmux_redis.egg-info/PKG-INFO
kmux_redis.egg-info/SOURCES.txt
kmux_redis.egg-info/dependency_links.txt
kmux_redis.egg-info/requires.txt
kmux_redis.egg-info/top_level.txt