Metadata-Version: 2.1
Name: kmux-redis
Version: 0.0.3
Summary: redis client
Home-page: https://gitee.com/muxiaofei/kmux-redis
Author: Mu Xiaofei
Author-email: me@muxiaofei.cn
License: UNKNOWN
Keywords: redis
Platform: UNKNOWN
Classifier: Programming Language :: Python :: 3
Classifier: License :: OSI Approved :: MIT License
Classifier: Operating System :: OS Independent
